{
  "unversionedId": "developer-resources/white-paper",
  "id": "developer-resources/white-paper",
  "title": "📄 White Paper",
  "description": "White Paper",
  "source": "@site/docs/developer-resources/white-paper.md",
  "sourceDirName": "developer-resources",
  "slug": "/developer-resources/white-paper",
  "permalink": "/developer-resources/white-paper",
  "draft": false,
  "editUrl": "https://github.com/facebook/docusaurus/tree/main/packages/create-docusaurus/templates/shared/docs/developer-resources/white-paper.md",
  "tags": [],
  "version": "current",
  "sidebarPosition": 9,
  "frontMatter": {
    "sidebar_label": "White Paper",
    "sidebar_position": 9,
    "description": "White Paper"
  },
  "sidebar": "tutorialSidebar",
  "previous": {
    "title": "0x Legal Guide",
    "permalink": "/developer-resources/0x-legal-guide"
  },
  "next": {
    "title": "Tutorial - Basics",
    "permalink": "/category/tutorial---basics"
  }
}